CHANGES
INSTALL
LICENSE
MANIFEST.in
README.rst
setup.cfg
setup.py
redis/__init__.py
redis/_compat.py
redis/client.py
redis/connection.py
redis/exceptions.py
redis/lock.py
redis/sentinel.py
redis/utils.py
redis_py_with_geo.egg-info/PKG-INFO
redis_py_with_geo.egg-info/SOURCES.txt
redis_py_with_geo.egg-info/dependency_links.txt
redis_py_with_geo.egg-info/top_level.txt
tests/__init__.py
tests/conftest.py
tests/test_commands.py
tests/test_connection_pool.py
tests/test_encoding.py
tests/test_lock.py
tests/test_pipeline.py
tests/test_pubsub.py
tests/test_scripting.py
tests/test_sentinel.py